olcarpc/__init__.py
olcarpc/generated/__init__.py
olcarpc/generated/about_service_pb2.py
olcarpc/generated/about_service_pb2_grpc.py
olcarpc/generated/commons_pb2.py
olcarpc/generated/commons_pb2_grpc.py
olcarpc/generated/data_fetch_service_pb2.py
olcarpc/generated/data_fetch_service_pb2_grpc.py
olcarpc/generated/data_update_service_pb2.py
olcarpc/generated/data_update_service_pb2_grpc.py
olcarpc/generated/flow_map_service_pb2.py
olcarpc/generated/flow_map_service_pb2_grpc.py
olcarpc/generated/olca_pb2.py
olcarpc/generated/olca_pb2_grpc.py
olcarpc/generated/result_service_pb2.py
olcarpc/generated/result_service_pb2_grpc.py
olcarpc-0.0.2.dist-info/LICENSE
olcarpc-0.0.2.dist-info/METADATA
olcarpc-0.0.2.dist-info/WHEEL
olcarpc-0.0.2.dist-info/top_level.txt
olcarpc-0.0.2.dist-info/RECORD
