Metadata-Version: 2.1
Name: olcarpc
Version: 0.0.2
Summary: A Python gRPC client library for openLCA.
Home-page: https://github.com/GreenDelta/olcarpc.py
License: UNKNOWN
Keywords: openLCA,life cycle assessment,LCA
Platform: UNKNOWN
Classifier: Development Status :: 2 - Pre-Alpha
Classifier: Environment :: Console
Classifier: Intended Audience :: Science/Research
Classifier: License :: OSI Approved :: Mozilla Public License 2.0 (MPL 2.0)
Classifier: Programming Language :: Python :: 3.7
Classifier: Topic :: Utilities
License-File: LICENSE
Requires-Dist: grpcio (>=1.47.0)
Requires-Dist: protobuf (>=3.20.1)
